xycmap/__init__.py
xycmap/xycmap.py
xycmap-1.0.1.dist-info/LICENSE
xycmap-1.0.1.dist-info/METADATA
xycmap-1.0.1.dist-info/WHEEL
xycmap-1.0.1.dist-info/top_level.txt
xycmap-1.0.1.dist-info/RECORD
