Metadata-Version: 2.1
Name: xycmap
Version: 1.0.1
Summary: Bivariate colormap solutions
Home-page: https://github.com/rbjansen/xycmap
Author: Remco Bastiaan Jansen
Author-email: r.b.jansen.uu@gmail.com
License: MIT
Keywords: visualization,colormap,color,bivariate,two-dimensional
Platform: UNKNOWN
Classifier: License :: OSI Approved :: MIT License
Classifier: Programming Language :: Python :: 3.8
Classifier: Intended Audience :: Science/Research
Classifier: Topic :: Scientific/Engineering :: Visualization
Requires-Dist: pandas
Requires-Dist: numpy
Requires-Dist: scipy
Requires-Dist: matplotlib
